image_processing_ord/__init__.py
image_processing_ord/processing/__init__.py
image_processing_ord/processing/combination.py
image_processing_ord/processing/transformation.py
image_processing_ord/utils/__init__.py
image_processing_ord/utils/io.py
image_processing_ord/utils/plot.py
image_processing_ord-0.0.2.dist-info/METADATA
image_processing_ord-0.0.2.dist-info/WHEEL
image_processing_ord-0.0.2.dist-info/top_level.txt
image_processing_ord-0.0.2.dist-info/RECORD
