Metadata-Version: 2.4
Name: image_processing_ord
Version: 0.0.2
Summary: Pacote de Processamento de Imagens
Author: ORD
Author-email: ord@gmail.com
Requires-Python: >=3.8
Requires-Dist: matplotlib
Requires-Dist: numpy
Requires-Dist: scikit-image>=0.16.1
Dynamic: author
Dynamic: author-email
Dynamic: description
Dynamic: description-content-type
Dynamic: requires-dist
Dynamic: requires-python
Dynamic: summary
